atfdb/__init__.py
atfdb/_version.py
atfdb/atfdb.py
atfdb/ophyd.py
atfdb/utils.py
atfdb/tests/__init__.py
atfdb/tests/conftest.py
atfdb/tests/socket_server.py
atfdb/tests/test_atfdb.py
atfdb/tests/test_ophyd.py
atfdb-0.3.0.dist-info/LICENSE
atfdb-0.3.0.dist-info/METADATA
atfdb-0.3.0.dist-info/WHEEL
atfdb-0.3.0.dist-info/entry_points.txt
atfdb-0.3.0.dist-info/top_level.txt
atfdb-0.3.0.dist-info/RECORD
