Metadata-Version: 2.1
Name: atfdb
Version: 0.3.0
Summary: BNL/ATF socket-based data acquisition client
Home-page: https://github.com/BNL-ATF/atfdb
Author: Brookhaven National Laboratory
Author-email: mrakitin@bnl.gov
License: BSD (3-clause)
Classifier: Development Status :: 2 - Pre-Alpha
Classifier: Natural Language :: English
Classifier: Programming Language :: Python :: 3
Requires-Python: >=3.7
License-File: LICENSE
Requires-Dist: ophyd
